qopt/__init__.py
qopt/amplitude_functions.py
qopt/analyser.py
qopt/cost_functions.py
qopt/data_container.py
qopt/energy_spectrum.py
qopt/matrix.py
qopt/noise.py
qopt/optimization_data.py
qopt/optimize.py
qopt/parallel.py
qopt/performance_statistics.py
qopt/plotting.py
qopt/simulator.py
qopt/solver_algorithms.py
qopt/transfer_function.py
qopt/util.py
qopt-1.3.5.dist-info/LICENSE
qopt-1.3.5.dist-info/METADATA
qopt-1.3.5.dist-info/WHEEL
qopt-1.3.5.dist-info/top_level.txt
qopt-1.3.5.dist-info/RECORD
